savvy_rest/__about__.py
savvy_rest/__init__.py
savvy_rest/cli/__init__.py
savvy_rest/cli/cli.py
savvy_rest/cli/cli_manager.py
savvy_rest/templates/structure.yaml
savvy_rest-0.0.1.dist-info/METADATA
savvy_rest-0.0.1.dist-info/WHEEL
savvy_rest-0.0.1.dist-info/entry_points.txt
savvy_rest-0.0.1.dist-info/licenses/LICENSE.txt
savvy_rest-0.0.1.dist-info/RECORD
